adversarylab/__init__.py
adversarylab/attacks/__init__.py
adversarylab/attacks/blackbox/__init__.py
adversarylab/attacks/whitebox/__init__.py
adversarylab/attacks/whitebox/wb_nontargeted_attack.py
adversarylab/attacks/whitebox/wb_targeted_attack.py
adversarylab/attacks/whitebox/whitebox_attack_base.py
adversarylab/core/__init__.py
adversarylab/core/getgrad/__init__.py
adversarylab/core/getgrad/getgrad.py
adversarylab/core/getgrad/getgrad_base.py
adversarylab/core/gradient_manipulation/__init__.py
adversarylab/core/gradient_manipulation/clipping.py
adversarylab/core/gradient_manipulation/gradient_manipulation_base.py
adversarylab/core/losses/__init__.py
adversarylab/core/losses/categorical_cross_entropy.py
adversarylab/core/losses/loss_base.py
adversarylab/core/losses/loss_registry.py
adversarylab/core/math/__init__.py
adversarylab/core/math/math.py
adversarylab/core/math/math_tf.py
adversarylab/core/math/math_torch.py
adversarylab/core/modelinfo/__init__.py
adversarylab/core/modelinfo/modelinfo.py
adversarylab/core/modelinfo/modelinfo_base.py
adversarylab/core/noise_generators/__init__.py
adversarylab/core/noise_generators/additive_noise_generator.py
adversarylab/core/noise_generators/noise_generator_base.py
adversarylab/core/optimizers/__init__.py
adversarylab/core/optimizers/adam.py
adversarylab/core/optimizers/optimizer_base.py
adversarylab/core/optimizers/optimizer_registry.py
adversarylab/core/preprocessing/__init__.py
adversarylab/core/preprocessing/no_preprocessing.py
adversarylab/core/preprocessing/preprocessing.py
adversarylab/core/preprocessing/preprocessing_from_function.py
adversarylab/core/tensor_ops/__init__.py
adversarylab/core/tensor_ops/tensor_ops.py
adversarylab/core/tensor_ops/tensor_tf.py
adversarylab/core/tensor_ops/tensor_torch.py
adversarylab/defenses/__init__.py
adversarylab/exceptions/__init__.py
adversarylab/exceptions/exceptions.py
tests/__init__.py
tests/attacks/__init__.py
tests/attacks/basic.py
tests/model/__init__.py
adversarylab-0.0.1rc0.dist-info/LICENSE
adversarylab-0.0.1rc0.dist-info/METADATA
adversarylab-0.0.1rc0.dist-info/WHEEL
adversarylab-0.0.1rc0.dist-info/top_level.txt
adversarylab-0.0.1rc0.dist-info/RECORD
