Metadata-Version: 2.1
Name: adversarylab
Version: 0.0.1rc0
Summary: A unified library for performing adversarial attacks on ML model to test their defense.
Home-page: https://github.com/pavanreddy-ml/adversarylab
Author: Pavan Reddy
Author-email: preddy.osdev@gmail.com
License: MIT
Platform: UNKNOWN
Classifier: Programming Language :: Python :: 3
Classifier: License :: OSI Approved :: MIT License
Classifier: Operating System :: OS Independent
Requires-Python: >=3.9
License-File: LICENSE
Requires-Dist: pytest
Requires-Dist: pytest-cov
Requires-Dist: flake8
Requires-Dist: mypy
Requires-Dist: Sphinx
Provides-Extra: testing
Requires-Dist: pytest ; extra == 'testing'
Requires-Dist: pytest-cov ; extra == 'testing'
